pyunit_time/__init__.py
pyunit_time/filters.py
pyunit_time/observer.py
pyunit_time/pytime.py
pyunit_time/re.txt
pyunit_time/pyunit_calendar/CTC_.py
pyunit_time/pyunit_calendar/LSC.py
pyunit_time/pyunit_calendar/SC_.py
pyunit_time/pyunit_calendar/__init__.py
pyunit_time/pyunit_calendar/batchcalendar.py
pyunit_time/pyunit_calendar/config.py
pyunit_time/pyunit_calendar/date.zip
pyunit_time/retime/__init__.py
pyunit_time/retime/days.py
pyunit_time/retime/formats.py
pyunit_time/retime/hours.py
pyunit_time/retime/lunarholiday.py
pyunit_time/retime/minutes.py
pyunit_time/retime/months.py
pyunit_time/retime/seconds.py
pyunit_time/retime/solarholiday.py
pyunit_time/retime/solarterm24.py
pyunit_time/retime/specialholiday.py
pyunit_time/retime/weeks.py
pyunit_time/retime/years.py
pyunit_time-2024.7.3.dist-info/METADATA
pyunit_time-2024.7.3.dist-info/WHEEL
pyunit_time-2024.7.3.dist-info/top_level.txt
pyunit_time-2024.7.3.dist-info/zip-safe
pyunit_time-2024.7.3.dist-info/RECORD
