Metadata-Version: 2.1
Name: pyunit-time
Version: 2024.7.3
Summary: 字符串时间解析
Home-page: https://github.com/PyUnit/pyunit-time
Author: 张伟
Author-email: jtyoui@qq.com
License: MIT Licence
Platform: any
Classifier: Programming Language :: Python :: 3
Classifier: License :: OSI Approved :: MIT License
Classifier: Operating System :: OS Independent
Requires-Dist: arrow
